mhn/__init__.py
mhn/dialect.py
mhn/reader.py
mhn/schema.py
mhn/utilities.py
mhn/writer.py
test/__init__.py
test/test_reader.py
test/test_schema.py
test/test_writer.py
sckism_mhn-0.0.5.dist-info/METADATA
sckism_mhn-0.0.5.dist-info/WHEEL
sckism_mhn-0.0.5.dist-info/top_level.txt
sckism_mhn-0.0.5.dist-info/RECORD
